my_library/__init__.py
my_library/core.py
my_library/utils.py
my_library_harry-1.0.0.dist-info/licenses/LICENSE
my_library_harry-1.0.0.dist-info/METADATA
my_library_harry-1.0.0.dist-info/WHEEL
my_library_harry-1.0.0.dist-info/top_level.txt
my_library_harry-1.0.0.dist-info/RECORD
