Metadata-Version: 2.4
Name: my-library-Harry
Version: 1.0.0
Summary: A simple Python library for math operations
Author-email: Harry <harry@agilex.ai>
Classifier: Programming Language :: Python :: 3
Classifier: License :: OSI Approved :: MIT License
Classifier: Operating System :: OS Independent
Requires-Python: >=3.8
License-File: LICENSE
Dynamic: license-file
